{
  "author_to_samples": {
    "Hsiao Yun": [
      0,
      1,
      2,
      3,
      4,
      5,
      6,
      7,
      8,
      9,
      10,
      11,
      12,
      13,
      14,
      15,
      16,
      17,
      18,
      19
    ],
    "Carmen Montenegro": [
      20,
      21,
      22,
      23,
      24,
      25,
      26,
      27,
      28,
      29,
      30,
      31,
      32,
      33,
      34,
      35,
      36,
      37,
      38,
      39
    ],
    "Elvin Mammadov": [
      40,
      41,
      42,
      43,
      44,
      45,
      46,
      47,
      48,
      49,
      50,
      51,
      52,
      53,
      54,
      55,
      56,
      57,
      58,
      59
    ],
    "Rajeev Majumdar": [
      60,
      61,
      62,
      63,
      64,
      65,
      66,
      67,
      68,
      69,
      70,
      71,
      72,
      73,
      74,
      75,
      76,
      77,
      78,
      79
    ],
    "Jad Ambrose": [
      80,
      81,
      82,
      83,
      84,
      85,
      86,
      87,
      88,
      89,
      90,
      91,
      92,
      93,
      94,
      95,
      96,
      97,
      98,
      99
    ],
    "Adib Jarrah": [
      100,
      101,
      102,
      103,
      104,
      105,
      106,
      107,
      108,
      109,
      110,
      111,
      112,
      113,
      114,
      115,
      116,
      117,
      118,
      119
    ],
    "Yeon Park": [
      120,
      121,
      122,
      123,
      124,
      125,
      126,
      127,
      128,
      129,
      130,
      131,
      132,
      133,
      134,
      135,
      136,
      137,
      138,
      139
    ],
    "Behrouz Rohani": [
      140,
      141,
      142,
      143,
      144,
      145,
      146,
      147,
      148,
      149,
      150,
      151,
      152,
      153,
      154,
      155,
      156,
      157,
      158,
      159
    ],
    "Jun Chen": [
      160,
      161,
      162,
      163,
      164,
      165,
      166,
      167,
      168,
      169,
      170,
      171,
      172,
      173,
      174,
      175,
      176,
      177,
      178,
      179
    ],
    "Hina Ameen": [
      200,
      201,
      202,
      203,
      204,
      205,
      206,
      207,
      208,
      209,
      210,
      211,
      212,
      213,
      214,
      215,
      216,
      217,
      218,
      219
    ],
    "Xin Lee": [
      220,
      221,
      222,
      223,
      224,
      225,
      226,
      227,
      228,
      229,
      230,
      231,
      232,
      233,
      234,
      235,
      236,
      237,
      238,
      239
    ],
    "Moshe Ben": [
      240,
      241,
      242,
      243,
      244,
      245,
      246,
      247,
      248,
      249,
      250,
      251,
      252,
      253,
      254,
      255,
      256,
      257,
      258,
      259
    ],
    "Kalkidan Abera": [
      260,
      261,
      262,
      263,
      264,
      265,
      266,
      267,
      268,
      269,
      270,
      271,
      272,
      273,
      274,
      275,
      276,
      277,
      278,
      279
    ],
    "Takashi Nakamura": [
      280,
      281,
      282,
      283,
      284,
      285,
      286,
      287,
      288,
      289,
      290,
      291,
      292,
      293,
      294,
      295,
      296,
      297,
      298,
      299
    ],
    "Raven Marais": [
      300,
      301,
      302,
      303,
      304,
      305,
      306,
      307,
      308,
      309,
      310,
      311,
      312,
      313,
      314,
      315,
      316,
      317,
      318,
      319
    ],
    "Aysha Al": [
      320,
      321,
      322,
      323,
      324,
      325,
      326,
      327,
      328,
      329,
      330,
      331,
      332,
      333,
      334,
      335,
      336,
      337,
      338,
      339
    ],
    "Patrick Sullivan": [
      340,
      341,
      342,
      343,
      344,
      345,
      346,
      347,
      348,
      349,
      350,
      351,
      352,
      353,
      354,
      355,
      356,
      357,
      358,
      359
    ],
    "Basil Mahfouz": [
      360,
      361,
      362,
      363,
      364,
      365,
      366,
      367,
      368,
      369,
      370,
      371,
      372,
      373,
      374,
      375,
      376,
      377,
      378,
      379
    ],
    "Nikolai Abilov": [
      380,
      381,
      382,
      383,
      384,
      385,
      386,
      387,
      388,
      389,
      390,
      391,
      392,
      393,
      394,
      395,
      396,
      397,
      398,
      399
    ]
  },
  "sample_to_author": {
    "0": "Hsiao Yun",
    "1": "Hsiao Yun",
    "2": "Hsiao Yun",
    "3": "Hsiao Yun",
    "4": "Hsiao Yun",
    "5": "Hsiao Yun",
    "6": "Hsiao Yun",
    "7": "Hsiao Yun",
    "8": "Hsiao Yun",
    "9": "Hsiao Yun",
    "10": "Hsiao Yun",
    "11": "Hsiao Yun",
    "12": "Hsiao Yun",
    "13": "Hsiao Yun",
    "14": "Hsiao Yun",
    "15": "Hsiao Yun",
    "16": "Hsiao Yun",
    "17": "Hsiao Yun",
    "18": "Hsiao Yun",
    "19": "Hsiao Yun",
    "20": "Carmen Montenegro",
    "21": "Carmen Montenegro",
    "22": "Carmen Montenegro",
    "23": "Carmen Montenegro",
    "24": "Carmen Montenegro",
    "25": "Carmen Montenegro",
    "26": "Carmen Montenegro",
    "27": "Carmen Montenegro",
    "28": "Carmen Montenegro",
    "29": "Carmen Montenegro",
    "30": "Carmen Montenegro",
    "31": "Carmen Montenegro",
    "32": "Carmen Montenegro",
    "33": "Carmen Montenegro",
    "34": "Carmen Montenegro",
    "35": "Carmen Montenegro",
    "36": "Carmen Montenegro",
    "37": "Carmen Montenegro",
    "38": "Carmen Montenegro",
    "39": "Carmen Montenegro",
    "40": "Elvin Mammadov",
    "41": "Elvin Mammadov",
    "42": "Elvin Mammadov",
    "43": "Elvin Mammadov",
    "44": "Elvin Mammadov",
    "45": "Elvin Mammadov",
    "46": "Elvin Mammadov",
    "47": "Elvin Mammadov",
    "48": "Elvin Mammadov",
    "49": "Elvin Mammadov",
    "50": "Elvin Mammadov",
    "51": "Elvin Mammadov",
    "52": "Elvin Mammadov",
    "53": "Elvin Mammadov",
    "54": "Elvin Mammadov",
    "55": "Elvin Mammadov",
    "56": "Elvin Mammadov",
    "57": "Elvin Mammadov",
    "58": "Elvin Mammadov",
    "59": "Elvin Mammadov",
    "60": "Rajeev Majumdar",
    "61": "Rajeev Majumdar",
    "62": "Rajeev Majumdar",
    "63": "Rajeev Majumdar",
    "64": "Rajeev Majumdar",
    "65": "Rajeev Majumdar",
    "66": "Rajeev Majumdar",
    "67": "Rajeev Majumdar",
    "68": "Rajeev Majumdar",
    "69": "Rajeev Majumdar",
    "70": "Rajeev Majumdar",
    "71": "Rajeev Majumdar",
    "72": "Rajeev Majumdar",
    "73": "Rajeev Majumdar",
    "74": "Rajeev Majumdar",
    "75": "Rajeev Majumdar",
    "76": "Rajeev Majumdar",
    "77": "Rajeev Majumdar",
    "78": "Rajeev Majumdar",
    "79": "Rajeev Majumdar",
    "80": "Jad Ambrose",
    "81": "Jad Ambrose",
    "82": "Jad Ambrose",
    "83": "Jad Ambrose",
    "84": "Jad Ambrose",
    "85": "Jad Ambrose",
    "86": "Jad Ambrose",
    "87": "Jad Ambrose",
    "88": "Jad Ambrose",
    "89": "Jad Ambrose",
    "90": "Jad Ambrose",
    "91": "Jad Ambrose",
    "92": "Jad Ambrose",
    "93": "Jad Ambrose",
    "94": "Jad Ambrose",
    "95": "Jad Ambrose",
    "96": "Jad Ambrose",
    "97": "Jad Ambrose",
    "98": "Jad Ambrose",
    "99": "Jad Ambrose",
    "100": "Adib Jarrah",
    "101": "Adib Jarrah",
    "102": "Adib Jarrah",
    "103": "Adib Jarrah",
    "104": "Adib Jarrah",
    "105": "Adib Jarrah",
    "106": "Adib Jarrah",
    "107": "Adib Jarrah",
    "108": "Adib Jarrah",
    "109": "Adib Jarrah",
    "110": "Adib Jarrah",
    "111": "Adib Jarrah",
    "112": "Adib Jarrah",
    "113": "Adib Jarrah",
    "115": "Adib Jarrah",
    "116": "Adib Jarrah",
    "117": "Adib Jarrah",
    "118": "Adib Jarrah",
    "119": "Adib Jarrah",
    "120": "Yeon Park",
    "121": "Yeon Park",
    "122": "Yeon Park",
    "123": "Yeon Park",
    "124": "Yeon Park",
    "125": "Yeon Park",
    "126": "Yeon Park",
    "127": "Yeon Park",
    "128": "Yeon Park",
    "129": "Yeon Park",
    "130": "Yeon Park",
    "131": "Yeon Park",
    "132": "Yeon Park",
    "133": "Yeon Park",
    "134": "Yeon Park",
    "135": "Yeon Park",
    "136": "Yeon Park",
    "137": "Yeon Park",
    "138": "Yeon Park",
    "139": "Yeon Park",
    "140": "Behrouz Rohani",
    "141": "Behrouz Rohani",
    "142": "Behrouz Rohani",
    "143": "Behrouz Rohani",
    "144": "Behrouz Rohani",
    "145": "Behrouz Rohani",
    "146": "Behrouz Rohani",
    "147": "Behrouz Rohani",
    "148": "Behrouz Rohani",
    "149": "Behrouz Rohani",
    "150": "Behrouz Rohani",
    "151": "Behrouz Rohani",
    "152": "Behrouz Rohani",
    "153": "Behrouz Rohani",
    "154": "Behrouz Rohani",
    "155": "Behrouz Rohani",
    "156": "Behrouz Rohani",
    "157": "Behrouz Rohani",
    "158": "Behrouz Rohani",
    "159": "Behrouz Rohani",
    "160": "Jun Chen",
    "161": "Jun Chen",
    "162": "Jun Chen",
    "163": "Jun Chen",
    "164": "Jun Chen",
    "165": "Jun Chen",
    "166": "Jun Chen",
    "167": "Jun Chen",
    "168": "Jun Chen",
    "169": "Jun Chen",
    "170": "Jun Chen",
    "171": "Jun Chen",
    "172": "Jun Chen",
    "173": "Jun Chen",
    "174": "Jun Chen",
    "175": "Jun Chen",
    "176": "Jun Chen",
    "177": "Jun Chen",
    "178": "Jun Chen",
    "179": "Jun Chen",
    "200": "Hina Ameen",
    "201": "Hina Ameen",
    "202": "Hina Ameen",
    "203": "Hina Ameen",
    "204": "Hina Ameen",
    "205": "Hina Ameen",
    "206": "Hina Ameen",
    "207": "Hina Ameen",
    "208": "Hina Ameen",
    "209": "Hina Ameen",
    "210": "Hina Ameen",
    "211": "Hina Ameen",
    "212": "Hina Ameen",
    "213": "Hina Ameen",
    "214": "Hina Ameen",
    "215": "Hina Ameen",
    "216": "Hina Ameen",
    "217": "Hina Ameen",
    "218": "Hina Ameen",
    "219": "Hina Ameen",
    "220": "Xin Lee",
    "221": "Xin Lee",
    "222": "Xin Lee",
    "223": "Xin Lee",
    "224": "Xin Lee",
    "225": "Xin Lee",
    "226": "Xin Lee",
    "227": "Xin Lee",
    "228": "Xin Lee",
    "229": "Xin Lee",
    "230": "Xin Lee",
    "231": "Xin Lee",
    "232": "Xin Lee",
    "233": "Xin Lee",
    "234": "Xin Lee",
    "235": "Xin Lee",
    "236": "Xin Lee",
    "237": "Xin Lee",
    "238": "Xin Lee",
    "239": "Xin Lee",
    "240": "Moshe Ben",
    "241": "Moshe Ben",
    "242": "Moshe Ben",
    "243": "Moshe Ben",
    "244": "Moshe Ben",
    "245": "Moshe Ben",
    "246": "Moshe Ben",
    "247": "Moshe Ben",
    "248": "Moshe Ben",
    "249": "Moshe Ben",
    "250": "Moshe Ben",
    "251": "Moshe Ben",
    "252": "Moshe Ben",
    "253": "Moshe Ben",
    "254": "Moshe Ben",
    "256": "Moshe Ben",
    "257": "Moshe Ben",
    "258": "Moshe Ben",
    "259": "Moshe Ben",
    "260": "Kalkidan Abera",
    "261": "Kalkidan Abera",
    "262": "Kalkidan Abera",
    "263": "Kalkidan Abera",
    "264": "Kalkidan Abera",
    "265": "Kalkidan Abera",
    "266": "Kalkidan Abera",
    "267": "Kalkidan Abera",
    "268": "Kalkidan Abera",
    "269": "Kalkidan Abera",
    "270": "Kalkidan Abera",
    "271": "Kalkidan Abera",
    "272": "Kalkidan Abera",
    "273": "Kalkidan Abera",
    "274": "Kalkidan Abera",
    "275": "Kalkidan Abera",
    "276": "Kalkidan Abera",
    "277": "Kalkidan Abera",
    "278": "Kalkidan Abera",
    "279": "Kalkidan Abera",
    "280": "Takashi Nakamura",
    "281": "Takashi Nakamura",
    "282": "Takashi Nakamura",
    "283": "Takashi Nakamura",
    "284": "Takashi Nakamura",
    "285": "Takashi Nakamura",
    "286": "Takashi Nakamura",
    "287": "Takashi Nakamura",
    "288": "Takashi Nakamura",
    "289": "Takashi Nakamura",
    "290": "Takashi Nakamura",
    "291": "Takashi Nakamura",
    "292": "Takashi Nakamura",
    "293": "Takashi Nakamura",
    "294": "Takashi Nakamura",
    "295": "Takashi Nakamura",
    "296": "Takashi Nakamura",
    "297": "Takashi Nakamura",
    "298": "Takashi Nakamura",
    "299": "Takashi Nakamura",
    "300": "Raven Marais",
    "301": "Raven Marais",
    "302": "Raven Marais",
    "303": "Raven Marais",
    "304": "Raven Marais",
    "305": "Raven Marais",
    "306": "Raven Marais",
    "307": "Raven Marais",
    "309": "Raven Marais",
    "310": "Raven Marais",
    "311": "Raven Marais",
    "312": "Raven Marais",
    "313": "Raven Marais",
    "314": "Raven Marais",
    "316": "Raven Marais",
    "317": "Raven Marais",
    "318": "Raven Marais",
    "319": "Raven Marais",
    "320": "Aysha Al",
    "321": "Aysha Al",
    "322": "Aysha Al",
    "323": "Aysha Al",
    "324": "Aysha Al",
    "325": "Aysha Al",
    "326": "Aysha Al",
    "327": "Aysha Al",
    "328": "Aysha Al",
    "329": "Aysha Al",
    "330": "Aysha Al",
    "331": "Aysha Al",
    "334": "Aysha Al",
    "335": "Aysha Al",
    "336": "Aysha Al",
    "337": "Aysha Al",
    "338": "Aysha Al",
    "339": "Aysha Al",
    "340": "Patrick Sullivan",
    "341": "Patrick Sullivan",
    "342": "Patrick Sullivan",
    "343": "Patrick Sullivan",
    "344": "Patrick Sullivan",
    "345": "Patrick Sullivan",
    "346": "Patrick Sullivan",
    "347": "Patrick Sullivan",
    "348": "Patrick Sullivan",
    "349": "Patrick Sullivan",
    "350": "Patrick Sullivan",
    "351": "Patrick Sullivan",
    "352": "Patrick Sullivan",
    "353": "Patrick Sullivan",
    "354": "Patrick Sullivan",
    "355": "Patrick Sullivan",
    "356": "Patrick Sullivan",
    "357": "Patrick Sullivan",
    "358": "Patrick Sullivan",
    "359": "Patrick Sullivan",
    "360": "Basil Mahfouz",
    "361": "Basil Mahfouz",
    "362": "Basil Mahfouz",
    "363": "Basil Mahfouz",
    "364": "Basil Mahfouz",
    "365": "Basil Mahfouz",
    "366": "Basil Mahfouz",
    "367": "Basil Mahfouz",
    "368": "Basil Mahfouz",
    "369": "Basil Mahfouz",
    "370": "Basil Mahfouz",
    "371": "Basil Mahfouz",
    "372": "Basil Mahfouz",
    "373": "Basil Mahfouz",
    "374": "Basil Mahfouz",
    "375": "Basil Mahfouz",
    "376": "Basil Mahfouz",
    "377": "Basil Mahfouz",
    "378": "Basil Mahfouz",
    "379": "Basil Mahfouz",
    "380": "Nikolai Abilov",
    "381": "Nikolai Abilov",
    "382": "Nikolai Abilov",
    "383": "Nikolai Abilov",
    "384": "Nikolai Abilov",
    "385": "Nikolai Abilov",
    "386": "Nikolai Abilov",
    "387": "Nikolai Abilov",
    "388": "Nikolai Abilov",
    "389": "Nikolai Abilov",
    "390": "Nikolai Abilov",
    "391": "Nikolai Abilov",
    "392": "Nikolai Abilov",
    "393": "Nikolai Abilov",
    "394": "Nikolai Abilov",
    "395": "Nikolai Abilov",
    "396": "Nikolai Abilov",
    "397": "Nikolai Abilov",
    "398": "Nikolai Abilov",
    "399": "Nikolai Abilov"
  },
  "author_stats": {
    "Hsiao Yun": 20,
    "Carmen Montenegro": 20,
    "Elvin Mammadov": 20,
    "Rajeev Majumdar": 20,
    "Jad Ambrose": 20,
    "Adib Jarrah": 20,
    "Yeon Park": 20,
    "Behrouz Rohani": 20,
    "Jun Chen": 20,
    "Hina Ameen": 20,
    "Xin Lee": 20,
    "Moshe Ben": 20,
    "Kalkidan Abera": 20,
    "Takashi Nakamura": 20,
    "Raven Marais": 20,
    "Aysha Al": 20,
    "Patrick Sullivan": 20,
    "Basil Mahfouz": 20,
    "Nikolai Abilov": 20
  }
}